executeline/__init__.py
executeline/execute.py
executeline/testing.py
executeline-0.1.1.dist-info/METADATA
executeline-0.1.1.dist-info/WHEEL
executeline-0.1.1.dist-info/top_level.txt
executeline-0.1.1.dist-info/RECORD
