Metadata-Version: 2.1
Name: executeline
Version: 0.1.1
Summary: Execute Callable Object in Line. ONE BY ONE.
Home-page: https://github.com/Class-Tooraj/ExecuteLine
Author: ToorajJahangiri
Author-email: Toorajjahangiri@gmail.com
License: MIT
Platform: UNKNOWN
Classifier: License :: OSI Approved :: MIT License
Classifier: Operating System :: OS Independent
Classifier: Programming Language :: Python :: 3.7
Classifier: Topic :: Software Development :: Libraries :: Python Modules
Requires-Python: >=3.7.*
